insertmap.py
insertmap-0.1.19.dist-info/LICENSE
insertmap-0.1.19.dist-info/METADATA
insertmap-0.1.19.dist-info/WHEEL
insertmap-0.1.19.dist-info/top_level.txt
insertmap-0.1.19.dist-info/RECORD
