Metadata-Version: 2.1
Name: insertmap
Version: 0.1.19
Summary: Map insertion sites to viral or microbial genome from wgs or lam-pcr data
Home-page: https://github.com/damienmarsic/insertmap
Author: Damien Marsic
Author-email: damien.marsic@aliyun.com
Classifier: Programming Language :: Python :: 3
Classifier: License :: OSI Approved :: GNU General Public License v3 (GPLv3)
Classifier: Operating System :: OS Independent
Classifier: Intended Audience :: Science/Research
Classifier: Topic :: Scientific/Engineering :: Bio-Informatics
Requires-Python: >=3.6
License-File: LICENSE
